strictpy/__init__.py
strictpy/decorator.py
strictpy/exceptions.py
strictpy/helpers.py
strictpy-1.1.0.dist-info/LICENSE
strictpy-1.1.0.dist-info/METADATA
strictpy-1.1.0.dist-info/WHEEL
strictpy-1.1.0.dist-info/top_level.txt
strictpy-1.1.0.dist-info/RECORD
