Metadata-Version: 2.1
Name: strictpy
Version: 1.1.0
Summary: This is a simple decorator that will allow you to implement strict type checking in your everyday cPython functions based on the type hint of the function parameters.
Author-email: Ishmam Hossain <ishmam.dev@gmail.com>
Project-URL: Homepage, https://github.com/ishmam-hossain/strictpy
Project-URL: Bug Tracker, https://github.com/ishmam-hossain/strictpy/issues
Classifier: Programming Language :: Python :: 3
Classifier: License :: OSI Approved :: MIT License
Classifier: Operating System :: OS Independent
Requires-Python: >=3.7
License-File: LICENSE
